{
  "quetta-joule-per-kelvin": 1e+30,
  "QK": 1e+30,
  "quettajoule-per-kelvin": 1e+30,
  "ronna-joule-per-kelvin": 1e+27,
  "ronnajoule-per-kelvin": 1e+27,
  "RK": 1e+27,
  "YK": 1e+24,
  "yotta-joule-per-kelvin": 1e+24,
  "yottajoule-per-kelvin": 1e+24,
  "zettajoule-per-kelvin": 1e+21,
  "ZK": 1e+21,
  "zetta-joule-per-kelvin": 1e+21,
  "exa-joule-per-kelvin": 1e+18,
  "EK": 1e+18,
  "exajoule-per-kelvin": 1e+18,
  "peta-joule-per-kelvin": 1000000000000000.0,
  "petajoule-per-kelvin": 1000000000000000.0,
  "PK": 1000000000000000.0,
  "tera-joule-per-kelvin": 1000000000000.0,
  "terajoule-per-kelvin": 1000000000000.0,
  "TK": 1000000000000.0,
  "giga-joule-per-kelvin": 1000000000.0,
  "GK": 1000000000.0,
  "gigajoule-per-kelvin": 1000000000.0,
  "mega-joule-per-kelvin": 1000000.0,
  "megajoule-per-kelvin": 1000000.0,
  "MK": 1000000.0,
  "kK": 1000.0,
  "kilojoule-per-kelvin": 1000.0,
  "kilo-joule-per-kelvin": 1000.0,
  "hecto-joule-per-kelvin": 100.0,
  "hK": 100.0,
  "hectojoule-per-kelvin": 100.0,
  "deka-joule-per-kelvin": 10.0,
  "dekajoule-per-kelvin": 10.0,
  "daK": 10.0,
  "jouleper-kelvin": 1.0,
  "joule-per-kelvin": 1.0,
  "deci-joule-per-kelvin": 0.1,
  "dK": 0.1,
  "decijoule-per-kelvin": 0.1,
  "cK": 0.01,
  "centi-joule-per-kelvin": 0.01,
  "centijoule-per-kelvin": 0.01,
  "mK": 0.001,
  "milli-joule-per-kelvin": 0.001,
  "millijoule-per-kelvin": 0.001,
  "\u03bcK": 1e-06,
  "micro-joule-per-kelvin": 1e-06,
  "microjoule-per-kelvin": 1e-06,
  "nanojoule-per-kelvin": 1e-09,
  "nano-joule-per-kelvin": 1e-09,
  "nK": 1e-09,
  "pico-joule-per-kelvin": 1e-12,
  "pK": 1e-12,
  "picojoule-per-kelvin": 1e-12,
  "femto-joule-per-kelvin": 1e-15,
  "fK": 1e-15,
  "femtojoule-per-kelvin": 1e-15,
  "atto-joule-per-kelvin": 1e-18,
  "aK": 1e-18,
  "attojoule-per-kelvin": 1e-18,
  "zeptojoule-per-kelvin": 1e-21,
  "zK": 1e-21,
  "zepto-joule-per-kelvin": 1e-21,
  "yocto-joule-per-kelvin": 1e-24,
  "yoctojoule-per-kelvin": 1e-24,
  "yK": 1e-24,
  "rK": 1e-27,
  "ronto-joule-per-kelvin": 1e-27,
  "rontojoule-per-kelvin": 1e-27,
  "quecto-joule-per-kelvin": 1e-30,
  "qK": 1e-30,
  "quectojoule-per-kelvin": 1e-30,
  "calorie-per-celsius": 4.184,
  "calorieper-celsius": 4.184
}